qualibrate_composite/__init__.py
qualibrate_composite/__main__.py
qualibrate_composite/api/__init__.py
qualibrate_composite/api/auth_middleware.py
qualibrate_composite/api/routes.py
qualibrate_composite/app.py
qualibrate_composite/cli/__init__.py
qualibrate_composite/cli/start.py
qualibrate_composite/config/__init__.py
qualibrate_composite/config/resolvers.py
qualibrate_composite/config/vars.py
qualibrate_composite/utils/__init__.py
qualibrate_composite/utils/logging_filter.py
qualibrate_composite/utils/spawn.py
qualibrate_examples/README.md
qualibrate_examples/__init__.py
qualibrate_examples/calibrations/01_demo_qubit_spectroscopy.py
qualibrate_examples/calibrations/02_demo_rabi.py
qualibrate_examples/calibrations/03_demo_chevron.py
qualibrate_examples/calibrations/04_demo_rabi_refined.py
qualibrate_examples/calibrations/05_demo_ramsey.py
qualibrate_examples/calibrations/06_demo_t1.py
qualibrate_examples/calibrations/07_demo_randomized_benchmarking.py
qualibrate_examples/calibrations/10_basic_graph_composition.py
qualibrate_examples/calibrations/11_tuneup_with_retries.py
qualibrate_examples/calibrations/12_adaptive_ramsey.py
qualibrate_examples/calibrations/13_full_qubit_characterization.py
qualibrate_examples/calibrations/__init__.py
qualibrate_examples/scripts/__init__.py
qualibrate_examples/scripts/generate_demo_quam_state.py
qualibrate-0.6.0.dist-info/METADATA
qualibrate-0.6.0.dist-info/WHEEL
qualibrate-0.6.0.dist-info/entry_points.txt
qualibrate-0.6.0.dist-info/licenses/LICENSE
qualibrate-0.6.0.dist-info/RECORD
